MANIFEST.in
setup.py
python_bin/supplescroll
supplescroll/.DS_Store
supplescroll/__init__.py
supplescroll/__init__.pyc
supplescroll/_version.py
supplescroll/_version.pyc
supplescroll/browserify.sh
supplescroll/build.js
supplescroll/clown.css
supplescroll/clown.sass
supplescroll/compile.sh
supplescroll/dark.css
supplescroll/dark.sass
supplescroll/install_modules.sh
supplescroll/light.css
supplescroll/light.sass
supplescroll/sassin.sh
supplescroll/sphinx.css
supplescroll/sphinx.sass
supplescroll/supplescroll.compiled.js
supplescroll/supplescroll.css
supplescroll/supplescroll.js
supplescroll/supplescroll.min.js
supplescroll/watchify.sh
supplescroll/yeolde.css
supplescroll/yeolde.sass
supplescroll.egg-info/PKG-INFO
supplescroll.egg-info/SOURCES.txt
supplescroll.egg-info/dependency_links.txt
supplescroll.egg-info/requires.txt
supplescroll.egg-info/top_level.txt