Metadata-Version: 1.0
Name: supplescroll
Version: 2.1.1
Summary: converts markdown to HTML with integrated table  of contents and figure panel, tied together with some supple scrolling
Home-page: http://boscoh.github.io/supplescroll
Author: Bosco Ho
Author-email: boscoh@gmail.com
License: BSD
Platform: UNKNOWN
